<annotation>
	<folder>dataset</folder>
	<filename>056.JPG</filename>
	<path>/Users/gwak2837/Python/UAV/Model/dataset/056.JPG</path>
	<source>
		<database>Unknown</database>
	</source>
	<size>
		<width>5184</width>
		<height>3456</height>
		<depth>3</depth>
	</size>
	<segmented>0</segmented>
	<object>
		<name>person</name>
		<pose>Unspecified</pose>
		<truncated>0</truncated>
		<difficult>0</difficult>
		<bndbox>
			<xmin>1982</xmin>
			<ymin>1770</ymin>
			<xmax>2287</xmax>
			<ymax>2155</ymax>
		</bndbox>
	</object>
	<object>
		<name>person</name>
		<pose>Unspecified</pose>
		<truncated>0</truncated>
		<difficult>0</difficult>
		<bndbox>
			<xmin>3642</xmin>
			<ymin>1405</ymin>
			<xmax>4067</xmax>
			<ymax>1925</ymax>
		</bndbox>
	</object>
	<object>
		<name>person</name>
		<pose>Unspecified</pose>
		<truncated>1</truncated>
		<difficult>0</difficult>
		<bndbox>
			<xmin>4577</xmin>
			<ymin>2130</ymin>
			<xmax>5184</xmax>
			<ymax>2635</ymax>
		</bndbox>
	</object>
	<object>
		<name>person</name>
		<pose>Unspecified</pose>
		<truncated>1</truncated>
		<difficult>0</difficult>
		<bndbox>
			<xmin>1</xmin>
			<ymin>1810</ymin>
			<xmax>541</xmax>
			<ymax>2360</ymax>
		</bndbox>
	</object>
	<object>
		<name>person</name>
		<pose>Unspecified</pose>
		<truncated>1</truncated>
		<difficult>0</difficult>
		<bndbox>
			<xmin>1</xmin>
			<ymin>2385</ymin>
			<xmax>231</xmax>
			<ymax>2735</ymax>
		</bndbox>
	</object>
	<object>
		<name>person</name>
		<pose>Unspecified</pose>
		<truncated>0</truncated>
		<difficult>0</difficult>
		<bndbox>
			<xmin>1387</xmin>
			<ymin>525</ymin>
			<xmax>1712</xmax>
			<ymax>1155</ymax>
		</bndbox>
	</object>
	<object>
		<name>person</name>
		<pose>Unspecified</pose>
		<truncated>0</truncated>
		<difficult>0</difficult>
		<bndbox>
			<xmin>1557</xmin>
			<ymin>345</ymin>
			<xmax>1862</xmax>
			<ymax>905</ymax>
		</bndbox>
	</object>
	<object>
		<name>person</name>
		<pose>Unspecified</pose>
		<truncated>0</truncated>
		<difficult>0</difficult>
		<bndbox>
			<xmin>626</xmin>
			<ymin>865</ymin>
			<xmax>906</xmax>
			<ymax>1260</ymax>
		</bndbox>
	</object>
	<object>
		<name>person</name>
		<pose>Unspecified</pose>
		<truncated>0</truncated>
		<difficult>0</difficult>
		<bndbox>
			<xmin>696</xmin>
			<ymin>675</ymin>
			<xmax>991</xmax>
			<ymax>1040</ymax>
		</bndbox>
	</object>
	<object>
		<name>person</name>
		<pose>Unspecified</pose>
		<truncated>0</truncated>
		<difficult>0</difficult>
		<bndbox>
			<xmin>3292</xmin>
			<ymin>910</ymin>
			<xmax>3557</xmax>
			<ymax>1515</ymax>
		</bndbox>
	</object>
	<object>
		<name>person</name>
		<pose>Unspecified</pose>
		<truncated>0</truncated>
		<difficult>0</difficult>
		<bndbox>
			<xmin>3377</xmin>
			<ymin>815</ymin>
			<xmax>3657</xmax>
			<ymax>1405</ymax>
		</bndbox>
	</object>
	<object>
		<name>person</name>
		<pose>Unspecified</pose>
		<truncated>0</truncated>
		<difficult>0</difficult>
		<bndbox>
			<xmin>906</xmin>
			<ymin>310</ymin>
			<xmax>1157</xmax>
			<ymax>880</ymax>
		</bndbox>
	</object>
	<object>
		<name>person</name>
		<pose>Unspecified</pose>
		<truncated>0</truncated>
		<difficult>0</difficult>
		<bndbox>
			<xmin>971</xmin>
			<ymin>160</ymin>
			<xmax>1407</xmax>
			<ymax>725</ymax>
		</bndbox>
	</object>
	<object>
		<name>person</name>
		<pose>Unspecified</pose>
		<truncated>0</truncated>
		<difficult>0</difficult>
		<bndbox>
			<xmin>86</xmin>
			<ymin>785</ymin>
			<xmax>336</xmax>
			<ymax>1155</ymax>
		</bndbox>
	</object>
	<object>
		<name>person</name>
		<pose>Unspecified</pose>
		<truncated>0</truncated>
		<difficult>0</difficult>
		<bndbox>
			<xmin>2827</xmin>
			<ymin>540</ymin>
			<xmax>3032</xmax>
			<ymax>1020</ymax>
		</bndbox>
	</object>
	<object>
		<name>person</name>
		<pose>Unspecified</pose>
		<truncated>0</truncated>
		<difficult>0</difficult>
		<bndbox>
			<xmin>3002</xmin>
			<ymin>410</ymin>
			<xmax>3287</xmax>
			<ymax>965</ymax>
		</bndbox>
	</object>
	<object>
		<name>person</name>
		<pose>Unspecified</pose>
		<truncated>0</truncated>
		<difficult>0</difficult>
		<bndbox>
			<xmin>4337</xmin>
			<ymin>115</ymin>
			<xmax>4582</xmax>
			<ymax>520</ymax>
		</bndbox>
	</object>
	<object>
		<name>person</name>
		<pose>Unspecified</pose>
		<truncated>0</truncated>
		<difficult>0</difficult>
		<bndbox>
			<xmin>4027</xmin>
			<ymin>1100</ymin>
			<xmax>4322</xmax>
			<ymax>1510</ymax>
		</bndbox>
	</object>
	<object>
		<name>person</name>
		<pose>Unspecified</pose>
		<truncated>0</truncated>
		<difficult>0</difficult>
		<bndbox>
			<xmin>4127</xmin>
			<ymin>925</ymin>
			<xmax>4372</xmax>
			<ymax>1205</ymax>
		</bndbox>
	</object>
	<object>
		<name>person</name>
		<pose>Unspecified</pose>
		<truncated>0</truncated>
		<difficult>0</difficult>
		<bndbox>
			<xmin>3327</xmin>
			<ymin>15</ymin>
			<xmax>3537</xmax>
			<ymax>560</ymax>
		</bndbox>
	</object>
	<object>
		<name>person</name>
		<pose>Unspecified</pose>
		<truncated>0</truncated>
		<difficult>0</difficult>
		<bndbox>
			<xmin>3487</xmin>
			<ymin>10</ymin>
			<xmax>3817</xmax>
			<ymax>620</ymax>
		</bndbox>
	</object>
	<object>
		<name>person</name>
		<pose>Unspecified</pose>
		<truncated>0</truncated>
		<difficult>0</difficult>
		<bndbox>
			<xmin>3107</xmin>
			<ymin>10</ymin>
			<xmax>3392</xmax>
			<ymax>475</ymax>
		</bndbox>
	</object>
	<object>
		<name>person</name>
		<pose>Unspecified</pose>
		<truncated>1</truncated>
		<difficult>0</difficult>
		<bndbox>
			<xmin>4852</xmin>
			<ymin>10</ymin>
			<xmax>5184</xmax>
			<ymax>390</ymax>
		</bndbox>
	</object>
</annotation>
