<annotation>
	<folder>dataset</folder>
	<filename>069.JPG</filename>
	<path>/Users/gwak2837/Python/UAV/Model/dataset/069.JPG</path>
	<source>
		<database>Unknown</database>
	</source>
	<size>
		<width>5184</width>
		<height>3456</height>
		<depth>3</depth>
	</size>
	<segmented>0</segmented>
	<object>
		<name>person</name>
		<pose>Unspecified</pose>
		<truncated>0</truncated>
		<difficult>0</difficult>
		<bndbox>
			<xmin>3357</xmin>
			<ymin>2165</ymin>
			<xmax>3952</xmax>
			<ymax>2590</ymax>
		</bndbox>
	</object>
	<object>
		<name>person</name>
		<pose>Unspecified</pose>
		<truncated>0</truncated>
		<difficult>0</difficult>
		<bndbox>
			<xmin>3412</xmin>
			<ymin>2610</ymin>
			<xmax>3972</xmax>
			<ymax>2825</ymax>
		</bndbox>
	</object>
</annotation>
