<annotation>
	<folder>resized_InfraredImg</folder>
	<filename>0227.JPG</filename>
	<path>C:\Users\kohaeun\anaconda3\envs\YOLO\UAV\Camera_infrared\resized_InfraredImg\0227.JPG</path>
	<source>
		<database>Unknown</database>
	</source>
	<size>
		<width>320</width>
		<height>320</height>
		<depth>3</depth>
	</size>
	<segmented>0</segmented>
	<object>
		<name>person</name>
		<pose>Unspecified</pose>
		<truncated>0</truncated>
		<difficult>0</difficult>
		<bndbox>
			<xmin>92</xmin>
			<ymin>136</ymin>
			<xmax>152</xmax>
			<ymax>232</ymax>
		</bndbox>
	</object>
</annotation>
